[
  {
    "number": 7200,
    "action": "skipped_changed_since_review",
    "reason": "snapshot changed"
  },
  {
    "number": 7597,
    "action": "skipped_changed_since_review",
    "reason": "updated_at changed"
  },
  {
    "number": 7957,
    "action": "skipped_changed_since_review",
    "reason": "snapshot changed"
  },
  {
    "number": 12811,
    "action": "skipped_already_closed",
    "reason": "state is closed"
  },
  {
    "number": 12838,
    "action": "skipped_already_closed",
    "reason": "state is closed"
  },
  {
    "number": 12867,
    "action": "skipped_already_closed",
    "reason": "state is closed"
  },
  {
    "number": 12880,
    "action": "skipped_already_closed",
    "reason": "state is closed"
  },
  {
    "number": 12975,
    "action": "skipped_already_closed",
    "reason": "state is closed"
  },
  {
    "number": 13024,
    "action": "skipped_already_closed",
    "reason": "state is closed"
  },
  {
    "number": 13059,
    "action": "skipped_already_closed",
    "reason": "state is closed"
  },
  {
    "number": 13133,
    "action": "skipped_already_closed",
    "reason": "state is closed"
  },
  {
    "number": 13206,
    "action": "skipped_already_closed",
    "reason": "state is closed"
  },
  {
    "number": 13238,
    "action": "skipped_already_closed",
    "reason": "state is closed"
  },
  {
    "number": 13245,
    "action": "skipped_already_closed",
    "reason": "state is closed"
  },
  {
    "number": 13329,
    "action": "skipped_already_closed",
    "reason": "state is closed"
  },
  {
    "number": 13358,
    "action": "skipped_already_closed",
    "reason": "state is closed"
  },
  {
    "number": 13380,
    "action": "skipped_already_closed",
    "reason": "state is closed"
  },
  {
    "number": 13392,
    "action": "skipped_already_closed",
    "reason": "state is closed"
  },
  {
    "number": 13419,
    "action": "skipped_already_closed",
    "reason": "state is closed"
  },
  {
    "number": 13423,
    "action": "skipped_already_closed",
    "reason": "state is closed"
  },
  {
    "number": 13426,
    "action": "skipped_already_closed",
    "reason": "state is closed"
  },
  {
    "number": 13499,
    "action": "skipped_already_closed",
    "reason": "state is closed"
  },
  {
    "number": 13513,
    "action": "skipped_already_closed",
    "reason": "state is closed"
  },
  {
    "number": 13533,
    "action": "skipped_already_closed",
    "reason": "state is closed"
  },
  {
    "number": 13545,
    "action": "skipped_already_closed",
    "reason": "state is closed"
  },
  {
    "number": 13553,
    "action": "skipped_already_closed",
    "reason": "state is closed"
  },
  {
    "number": 13562,
    "action": "skipped_already_closed",
    "reason": "state is closed"
  },
  {
    "number": 13587,
    "action": "skipped_already_closed",
    "reason": "state is closed"
  },
  {
    "number": 13598,
    "action": "skipped_already_closed",
    "reason": "state is closed"
  },
  {
    "number": 13599,
    "action": "skipped_already_closed",
    "reason": "state is closed"
  },
  {
    "number": 13608,
    "action": "skipped_already_closed",
    "reason": "state is closed"
  },
  {
    "number": 13609,
    "action": "skipped_already_closed",
    "reason": "state is closed"
  },
  {
    "number": 13656,
    "action": "skipped_already_closed",
    "reason": "state is closed"
  },
  {
    "number": 13657,
    "action": "skipped_already_closed",
    "reason": "state is closed"
  },
  {
    "number": 13660,
    "action": "skipped_already_closed",
    "reason": "state is closed"
  },
  {
    "number": 13754,
    "action": "skipped_already_closed",
    "reason": "state is closed"
  },
  {
    "number": 13760,
    "action": "skipped_already_closed",
    "reason": "state is closed"
  },
  {
    "number": 13769,
    "action": "skipped_already_closed",
    "reason": "state is closed"
  },
  {
    "number": 13776,
    "action": "skipped_already_closed",
    "reason": "state is closed"
  },
  {
    "number": 13781,
    "action": "skipped_already_closed",
    "reason": "state is closed"
  },
  {
    "number": 13858,
    "action": "skipped_already_closed",
    "reason": "state is closed"
  },
  {
    "number": 13860,
    "action": "skipped_already_closed",
    "reason": "state is closed"
  },
  {
    "number": 13871,
    "action": "skipped_already_closed",
    "reason": "state is closed"
  },
  {
    "number": 13900,
    "action": "skipped_already_closed",
    "reason": "state is closed"
  },
  {
    "number": 13923,
    "action": "skipped_already_closed",
    "reason": "state is closed"
  },
  {
    "number": 13966,
    "action": "skipped_already_closed",
    "reason": "state is closed"
  },
  {
    "number": 14008,
    "action": "skipped_already_closed",
    "reason": "state is closed"
  },
  {
    "number": 14044,
    "action": "skipped_already_closed",
    "reason": "state is closed"
  },
  {
    "number": 14049,
    "action": "skipped_already_closed",
    "reason": "state is closed"
  },
  {
    "number": 14059,
    "action": "skipped_already_closed",
    "reason": "state is closed"
  },
  {
    "number": 14083,
    "action": "skipped_already_closed",
    "reason": "state is closed"
  },
  {
    "number": 14084,
    "action": "skipped_already_closed",
    "reason": "state is closed"
  },
  {
    "number": 14129,
    "action": "skipped_already_closed",
    "reason": "state is closed"
  },
  {
    "number": 14159,
    "action": "skipped_already_closed",
    "reason": "state is closed"
  },
  {
    "number": 14180,
    "action": "skipped_already_closed",
    "reason": "state is closed"
  },
  {
    "number": 14210,
    "action": "skipped_already_closed",
    "reason": "state is closed"
  },
  {
    "number": 14329,
    "action": "skipped_already_closed",
    "reason": "state is closed"
  },
  {
    "number": 14351,
    "action": "skipped_already_closed",
    "reason": "state is closed"
  },
  {
    "number": 14386,
    "action": "skipped_already_closed",
    "reason": "state is closed"
  },
  {
    "number": 14427,
    "action": "skipped_already_closed",
    "reason": "state is closed"
  },
  {
    "number": 14428,
    "action": "skipped_already_closed",
    "reason": "state is closed"
  },
  {
    "number": 14431,
    "action": "skipped_already_closed",
    "reason": "state is closed"
  },
  {
    "number": 14495,
    "action": "skipped_already_closed",
    "reason": "state is closed"
  },
  {
    "number": 14513,
    "action": "skipped_already_closed",
    "reason": "state is closed"
  },
  {
    "number": 14606,
    "action": "skipped_already_closed",
    "reason": "state is closed"
  },
  {
    "number": 14607,
    "action": "skipped_already_closed",
    "reason": "state is closed"
  },
  {
    "number": 14688,
    "action": "skipped_already_closed",
    "reason": "state is closed"
  },
  {
    "number": 14710,
    "action": "skipped_already_closed",
    "reason": "state is closed"
  },
  {
    "number": 14735,
    "action": "skipped_already_closed",
    "reason": "state is closed"
  },
  {
    "number": 14779,
    "action": "skipped_already_closed",
    "reason": "state is closed"
  },
  {
    "number": 14803,
    "action": "skipped_already_closed",
    "reason": "state is closed"
  },
  {
    "number": 14812,
    "action": "skipped_already_closed",
    "reason": "state is closed"
  },
  {
    "number": 14916,
    "action": "skipped_already_closed",
    "reason": "state is closed"
  },
  {
    "number": 14921,
    "action": "skipped_already_closed",
    "reason": "state is closed"
  },
  {
    "number": 14965,
    "action": "skipped_already_closed",
    "reason": "state is closed"
  },
  {
    "number": 15014,
    "action": "skipped_already_closed",
    "reason": "state is closed"
  },
  {
    "number": 15027,
    "action": "skipped_already_closed",
    "reason": "state is closed"
  },
  {
    "number": 15033,
    "action": "skipped_already_closed",
    "reason": "state is closed"
  },
  {
    "number": 15048,
    "action": "skipped_already_closed",
    "reason": "state is closed"
  },
  {
    "number": 15066,
    "action": "skipped_already_closed",
    "reason": "state is closed"
  },
  {
    "number": 15098,
    "action": "skipped_already_closed",
    "reason": "state is closed"
  },
  {
    "number": 15267,
    "action": "skipped_already_closed",
    "reason": "state is closed"
  },
  {
    "number": 15413,
    "action": "skipped_already_closed",
    "reason": "state is closed"
  },
  {
    "number": 15631,
    "action": "skipped_already_closed",
    "reason": "state is closed"
  },
  {
    "number": 15633,
    "action": "skipped_already_closed",
    "reason": "state is closed"
  },
  {
    "number": 15758,
    "action": "skipped_already_closed",
    "reason": "state is closed"
  },
  {
    "number": 15823,
    "action": "skipped_already_closed",
    "reason": "state is closed"
  },
  {
    "number": 15869,
    "action": "skipped_already_closed",
    "reason": "state is closed"
  },
  {
    "number": 15997,
    "action": "skipped_already_closed",
    "reason": "state is closed"
  },
  {
    "number": 16022,
    "action": "skipped_already_closed",
    "reason": "state is closed"
  },
  {
    "number": 16050,
    "action": "skipped_already_closed",
    "reason": "state is closed"
  },
  {
    "number": 16092,
    "action": "skipped_already_closed",
    "reason": "state is closed"
  },
  {
    "number": 16107,
    "action": "skipped_already_closed",
    "reason": "state is closed"
  },
  {
    "number": 16214,
    "action": "skipped_already_closed",
    "reason": "state is closed"
  },
  {
    "number": 16255,
    "action": "skipped_already_closed",
    "reason": "state is closed"
  },
  {
    "number": 16332,
    "action": "skipped_already_closed",
    "reason": "state is closed"
  },
  {
    "number": 16365,
    "action": "skipped_changed_since_review",
    "reason": "snapshot changed"
  },
  {
    "number": 16440,
    "action": "skipped_already_closed",
    "reason": "state is closed"
  },
  {
    "number": 16458,
    "action": "skipped_already_closed",
    "reason": "state is closed"
  },
  {
    "number": 16939,
    "action": "skipped_already_closed",
    "reason": "state is closed"
  },
  {
    "number": 17068,
    "action": "skipped_already_closed",
    "reason": "state is closed"
  },
  {
    "number": 17072,
    "action": "skipped_already_closed",
    "reason": "state is closed"
  },
  {
    "number": 17101,
    "action": "skipped_changed_since_review",
    "reason": "updated_at changed"
  },
  {
    "number": 17199,
    "action": "skipped_already_closed",
    "reason": "state is closed"
  },
  {
    "number": 17208,
    "action": "skipped_already_closed",
    "reason": "state is closed"
  },
  {
    "number": 17209,
    "action": "skipped_already_closed",
    "reason": "state is closed"
  },
  {
    "number": 17210,
    "action": "skipped_already_closed",
    "reason": "state is closed"
  },
  {
    "number": 17255,
    "action": "skipped_already_closed",
    "reason": "state is closed"
  },
  {
    "number": 17317,
    "action": "skipped_already_closed",
    "reason": "state is closed"
  },
  {
    "number": 17335,
    "action": "skipped_already_closed",
    "reason": "state is closed"
  },
  {
    "number": 17344,
    "action": "skipped_already_closed",
    "reason": "state is closed"
  },
  {
    "number": 17468,
    "action": "skipped_already_closed",
    "reason": "state is closed"
  },
  {
    "number": 17734,
    "action": "skipped_already_closed",
    "reason": "state is closed"
  },
  {
    "number": 17890,
    "action": "skipped_already_closed",
    "reason": "state is closed"
  },
  {
    "number": 17936,
    "action": "skipped_already_closed",
    "reason": "state is closed"
  },
  {
    "number": 18047,
    "action": "skipped_already_closed",
    "reason": "state is closed"
  },
  {
    "number": 18223,
    "action": "skipped_already_closed",
    "reason": "state is closed"
  },
  {
    "number": 18599,
    "action": "skipped_already_closed",
    "reason": "state is closed"
  },
  {
    "number": 18633,
    "action": "skipped_already_closed",
    "reason": "state is closed"
  },
  {
    "number": 18716,
    "action": "skipped_already_closed",
    "reason": "state is closed"
  },
  {
    "number": 18810,
    "action": "skipped_already_closed",
    "reason": "state is closed"
  },
  {
    "number": 18844,
    "action": "skipped_already_closed",
    "reason": "state is closed"
  },
  {
    "number": 18869,
    "action": "skipped_already_closed",
    "reason": "state is closed"
  },
  {
    "number": 18920,
    "action": "skipped_already_closed",
    "reason": "state is closed"
  },
  {
    "number": 19089,
    "action": "skipped_already_closed",
    "reason": "state is closed"
  },
  {
    "number": 19396,
    "action": "skipped_already_closed",
    "reason": "state is closed"
  },
  {
    "number": 19688,
    "action": "skipped_already_closed",
    "reason": "state is closed"
  },
  {
    "number": 19700,
    "action": "skipped_already_closed",
    "reason": "state is closed"
  },
  {
    "number": 19715,
    "action": "skipped_already_closed",
    "reason": "state is closed"
  },
  {
    "number": 19749,
    "action": "skipped_already_closed",
    "reason": "state is closed"
  },
  {
    "number": 19777,
    "action": "skipped_already_closed",
    "reason": "state is closed"
  },
  {
    "number": 19898,
    "action": "skipped_already_closed",
    "reason": "state is closed"
  },
  {
    "number": 19936,
    "action": "skipped_already_closed",
    "reason": "state is closed"
  },
  {
    "number": 20177,
    "action": "skipped_already_closed",
    "reason": "state is closed"
  },
  {
    "number": 20206,
    "action": "skipped_already_closed",
    "reason": "state is closed"
  },
  {
    "number": 20322,
    "action": "skipped_already_closed",
    "reason": "state is closed"
  },
  {
    "number": 20487,
    "action": "skipped_already_closed",
    "reason": "state is closed"
  },
  {
    "number": 20580,
    "action": "skipped_already_closed",
    "reason": "state is closed"
  },
  {
    "number": 20909,
    "action": "skipped_already_closed",
    "reason": "state is closed"
  },
  {
    "number": 21047,
    "action": "skipped_already_closed",
    "reason": "state is closed"
  },
  {
    "number": 21133,
    "action": "skipped_already_closed",
    "reason": "state is closed"
  },
  {
    "number": 21151,
    "action": "skipped_already_closed",
    "reason": "state is closed"
  },
  {
    "number": 21157,
    "action": "skipped_already_closed",
    "reason": "state is closed"
  },
  {
    "number": 21175,
    "action": "skipped_already_closed",
    "reason": "state is closed"
  },
  {
    "number": 21414,
    "action": "skipped_already_closed",
    "reason": "state is closed"
  },
  {
    "number": 21540,
    "action": "skipped_already_closed",
    "reason": "state is closed"
  },
  {
    "number": 21598,
    "action": "skipped_already_closed",
    "reason": "state is closed"
  },
  {
    "number": 21656,
    "action": "skipped_already_closed",
    "reason": "state is closed"
  },
  {
    "number": 21691,
    "action": "skipped_already_closed",
    "reason": "state is closed"
  },
  {
    "number": 21704,
    "action": "skipped_already_closed",
    "reason": "state is closed"
  },
  {
    "number": 21739,
    "action": "skipped_already_closed",
    "reason": "state is closed"
  },
  {
    "number": 21844,
    "action": "skipped_already_closed",
    "reason": "state is closed"
  },
  {
    "number": 21924,
    "action": "skipped_already_closed",
    "reason": "state is closed"
  },
  {
    "number": 22014,
    "action": "skipped_already_closed",
    "reason": "state is closed"
  },
  {
    "number": 22073,
    "action": "skipped_already_closed",
    "reason": "state is closed"
  },
  {
    "number": 22155,
    "action": "skipped_already_closed",
    "reason": "state is closed"
  },
  {
    "number": 22199,
    "action": "skipped_already_closed",
    "reason": "state is closed"
  },
  {
    "number": 22255,
    "action": "skipped_already_closed",
    "reason": "state is closed"
  },
  {
    "number": 22328,
    "action": "skipped_already_closed",
    "reason": "state is closed"
  },
  {
    "number": 22552,
    "action": "skipped_already_closed",
    "reason": "state is closed"
  },
  {
    "number": 22590,
    "action": "skipped_already_closed",
    "reason": "state is closed"
  },
  {
    "number": 22603,
    "action": "skipped_already_closed",
    "reason": "state is closed"
  },
  {
    "number": 22631,
    "action": "skipped_already_closed",
    "reason": "state is closed"
  },
  {
    "number": 22635,
    "action": "skipped_already_closed",
    "reason": "state is closed"
  },
  {
    "number": 22724,
    "action": "skipped_already_closed",
    "reason": "state is closed"
  },
  {
    "number": 22927,
    "action": "skipped_already_closed",
    "reason": "state is closed"
  },
  {
    "number": 23097,
    "action": "skipped_already_closed",
    "reason": "state is closed"
  },
  {
    "number": 23208,
    "action": "skipped_already_closed",
    "reason": "state is closed"
  },
  {
    "number": 23500,
    "action": "skipped_already_closed",
    "reason": "state is closed"
  },
  {
    "number": 23653,
    "action": "skipped_already_closed",
    "reason": "state is closed"
  },
  {
    "number": 23973,
    "action": "skipped_already_closed",
    "reason": "state is closed"
  },
  {
    "number": 24076,
    "action": "skipped_already_closed",
    "reason": "state is closed"
  },
  {
    "number": 24098,
    "action": "skipped_already_closed",
    "reason": "state is closed"
  },
  {
    "number": 24240,
    "action": "skipped_already_closed",
    "reason": "state is closed"
  },
  {
    "number": 24394,
    "action": "skipped_already_closed",
    "reason": "state is closed"
  },
  {
    "number": 24553,
    "action": "skipped_already_closed",
    "reason": "state is closed"
  },
  {
    "number": 24585,
    "action": "skipped_already_closed",
    "reason": "state is closed"
  },
  {
    "number": 24633,
    "action": "skipped_already_closed",
    "reason": "state is closed"
  },
  {
    "number": 24636,
    "action": "skipped_already_closed",
    "reason": "state is closed"
  },
  {
    "number": 24662,
    "action": "skipped_already_closed",
    "reason": "state is closed"
  },
  {
    "number": 24674,
    "action": "skipped_already_closed",
    "reason": "state is closed"
  },
  {
    "number": 24892,
    "action": "skipped_changed_since_review",
    "reason": "updated_at changed"
  },
  {
    "number": 24940,
    "action": "skipped_already_closed",
    "reason": "state is closed"
  },
  {
    "number": 24958,
    "action": "skipped_already_closed",
    "reason": "state is closed"
  },
  {
    "number": 25237,
    "action": "skipped_already_closed",
    "reason": "state is closed"
  },
  {
    "number": 25252,
    "action": "skipped_already_closed",
    "reason": "state is closed"
  },
  {
    "number": 25361,
    "action": "skipped_already_closed",
    "reason": "state is closed"
  },
  {
    "number": 25423,
    "action": "skipped_already_closed",
    "reason": "state is closed"
  },
  {
    "number": 25466,
    "action": "skipped_already_closed",
    "reason": "state is closed"
  },
  {
    "number": 25693,
    "action": "skipped_already_closed",
    "reason": "state is closed"
  },
  {
    "number": 25929,
    "action": "skipped_already_closed",
    "reason": "state is closed"
  },
  {
    "number": 25963,
    "action": "skipped_already_closed",
    "reason": "state is closed"
  },
  {
    "number": 26096,
    "action": "skipped_already_closed",
    "reason": "state is closed"
  },
  {
    "number": 26277,
    "action": "skipped_already_closed",
    "reason": "state is closed"
  },
  {
    "number": 26495,
    "action": "skipped_already_closed",
    "reason": "state is closed"
  },
  {
    "number": 26691,
    "action": "skipped_already_closed",
    "reason": "state is closed"
  },
  {
    "number": 26750,
    "action": "skipped_already_closed",
    "reason": "state is closed"
  },
  {
    "number": 26830,
    "action": "skipped_already_closed",
    "reason": "state is closed"
  },
  {
    "number": 27396,
    "action": "skipped_already_closed",
    "reason": "state is closed"
  },
  {
    "number": 27848,
    "action": "skipped_already_closed",
    "reason": "state is closed"
  },
  {
    "number": 27851,
    "action": "skipped_already_closed",
    "reason": "state is closed"
  },
  {
    "number": 27925,
    "action": "skipped_already_closed",
    "reason": "state is closed"
  },
  {
    "number": 28037,
    "action": "skipped_already_closed",
    "reason": "state is closed"
  },
  {
    "number": 28106,
    "action": "skipped_changed_since_review",
    "reason": "updated_at changed"
  },
  {
    "number": 28222,
    "action": "skipped_changed_since_review",
    "reason": "snapshot changed"
  },
  {
    "number": 28230,
    "action": "skipped_already_closed",
    "reason": "state is closed"
  },
  {
    "number": 28281,
    "action": "skipped_already_closed",
    "reason": "state is closed"
  },
  {
    "number": 28580,
    "action": "skipped_already_closed",
    "reason": "state is closed"
  },
  {
    "number": 28753,
    "action": "skipped_already_closed",
    "reason": "state is closed"
  },
  {
    "number": 28797,
    "action": "skipped_already_closed",
    "reason": "state is closed"
  },
  {
    "number": 28814,
    "action": "skipped_already_closed",
    "reason": "state is closed"
  },
  {
    "number": 29012,
    "action": "skipped_already_closed",
    "reason": "state is closed"
  },
  {
    "number": 29053,
    "action": "skipped_already_closed",
    "reason": "state is closed"
  },
  {
    "number": 29054,
    "action": "skipped_already_closed",
    "reason": "state is closed"
  },
  {
    "number": 29076,
    "action": "skipped_already_closed",
    "reason": "state is closed"
  },
  {
    "number": 29196,
    "action": "skipped_already_closed",
    "reason": "state is closed"
  },
  {
    "number": 29214,
    "action": "skipped_already_closed",
    "reason": "state is closed"
  },
  {
    "number": 29408,
    "action": "skipped_already_closed",
    "reason": "state is closed"
  },
  {
    "number": 29529,
    "action": "skipped_already_closed",
    "reason": "state is closed"
  },
  {
    "number": 29592,
    "action": "skipped_already_closed",
    "reason": "state is closed"
  },
  {
    "number": 29670,
    "action": "skipped_changed_since_review",
    "reason": "snapshot changed"
  },
  {
    "number": 29745,
    "action": "skipped_already_closed",
    "reason": "state is closed"
  },
  {
    "number": 29809,
    "action": "skipped_changed_since_review",
    "reason": "updated_at changed"
  },
  {
    "number": 29878,
    "action": "skipped_already_closed",
    "reason": "state is closed"
  },
  {
    "number": 29889,
    "action": "skipped_already_closed",
    "reason": "state is closed"
  },
  {
    "number": 29906,
    "action": "skipped_already_closed",
    "reason": "state is closed"
  },
  {
    "number": 29928,
    "action": "skipped_already_closed",
    "reason": "state is closed"
  },
  {
    "number": 30062,
    "action": "skipped_already_closed",
    "reason": "state is closed"
  },
  {
    "number": 30517,
    "action": "skipped_already_closed",
    "reason": "state is closed"
  },
  {
    "number": 30531,
    "action": "skipped_already_closed",
    "reason": "state is closed"
  },
  {
    "number": 30622,
    "action": "skipped_already_closed",
    "reason": "state is closed"
  },
  {
    "number": 30827,
    "action": "skipped_already_closed",
    "reason": "state is closed"
  },
  {
    "number": 30929,
    "action": "skipped_already_closed",
    "reason": "state is closed"
  },
  {
    "number": 30959,
    "action": "skipped_already_closed",
    "reason": "state is closed"
  },
  {
    "number": 30992,
    "action": "skipped_already_closed",
    "reason": "state is closed"
  },
  {
    "number": 30995,
    "action": "skipped_already_closed",
    "reason": "state is closed"
  },
  {
    "number": 30998,
    "action": "skipped_already_closed",
    "reason": "state is closed"
  },
  {
    "number": 31345,
    "action": "skipped_already_closed",
    "reason": "state is closed"
  },
  {
    "number": 31486,
    "action": "skipped_changed_since_review",
    "reason": "snapshot changed"
  },
  {
    "number": 31514,
    "action": "skipped_already_closed",
    "reason": "state is closed"
  },
  {
    "number": 31708,
    "action": "skipped_changed_since_review",
    "reason": "updated_at changed"
  },
  {
    "number": 31774,
    "action": "skipped_already_closed",
    "reason": "state is closed"
  },
  {
    "number": 31970,
    "action": "skipped_already_closed",
    "reason": "state is closed"
  },
  {
    "number": 31980,
    "action": "skipped_already_closed",
    "reason": "state is closed"
  },
  {
    "number": 32264,
    "action": "skipped_already_closed",
    "reason": "state is closed"
  },
  {
    "number": 32369,
    "action": "skipped_already_closed",
    "reason": "state is closed"
  },
  {
    "number": 32451,
    "action": "skipped_already_closed",
    "reason": "state is closed"
  },
  {
    "number": 32460,
    "action": "skipped_already_closed",
    "reason": "state is closed"
  },
  {
    "number": 32603,
    "action": "skipped_already_closed",
    "reason": "state is closed"
  },
  {
    "number": 32607,
    "action": "skipped_already_closed",
    "reason": "state is closed"
  },
  {
    "number": 32694,
    "action": "skipped_already_closed",
    "reason": "state is closed"
  },
  {
    "number": 32864,
    "action": "skipped_already_closed",
    "reason": "state is closed"
  },
  {
    "number": 33017,
    "action": "skipped_already_closed",
    "reason": "state is closed"
  },
  {
    "number": 33063,
    "action": "skipped_already_closed",
    "reason": "state is closed"
  },
  {
    "number": 33072,
    "action": "skipped_changed_since_review",
    "reason": "updated_at changed"
  },
  {
    "number": 33106,
    "action": "skipped_already_closed",
    "reason": "state is closed"
  },
  {
    "number": 33179,
    "action": "skipped_already_closed",
    "reason": "state is closed"
  },
  {
    "number": 33398,
    "action": "skipped_already_closed",
    "reason": "state is closed"
  },
  {
    "number": 33506,
    "action": "skipped_already_closed",
    "reason": "state is closed"
  },
  {
    "number": 33585,
    "action": "skipped_already_closed",
    "reason": "state is closed"
  },
  {
    "number": 33597,
    "action": "skipped_already_closed",
    "reason": "state is closed"
  },
  {
    "number": 33654,
    "action": "skipped_already_closed",
    "reason": "state is closed"
  },
  {
    "number": 33750,
    "action": "skipped_already_closed",
    "reason": "state is closed"
  },
  {
    "number": 33819,
    "action": "skipped_already_closed",
    "reason": "state is closed"
  },
  {
    "number": 34026,
    "action": "skipped_already_closed",
    "reason": "state is closed"
  },
  {
    "number": 34097,
    "action": "skipped_already_closed",
    "reason": "state is closed"
  },
  {
    "number": 34108,
    "action": "closed",
    "reason": "already implemented on main"
  },
  {
    "number": 34239,
    "action": "closed",
    "reason": "not actionable"
  },
  {
    "number": 34311,
    "action": "closed",
    "reason": "already implemented on main"
  },
  {
    "number": 34358,
    "action": "closed",
    "reason": "already implemented on main"
  },
  {
    "number": 34431,
    "action": "closed",
    "reason": "already implemented on main"
  },
  {
    "number": 34507,
    "action": "closed",
    "reason": "already implemented on main"
  },
  {
    "number": 34518,
    "action": "closed",
    "reason": "already implemented on main"
  },
  {
    "number": 34626,
    "action": "closed",
    "reason": "already implemented on main"
  },
  {
    "number": 34644,
    "action": "skipped_changed_since_review",
    "reason": "updated_at changed"
  },
  {
    "number": 34863,
    "action": "skipped_changed_since_review",
    "reason": "snapshot changed"
  },
  {
    "number": 35023,
    "action": "skipped_changed_since_review",
    "reason": "updated_at changed"
  },
  {
    "number": 35059,
    "action": "closed",
    "reason": "belongs on ClawHub"
  },
  {
    "number": 35071,
    "action": "closed",
    "reason": "belongs on ClawHub"
  },
  {
    "number": 35127,
    "action": "closed",
    "reason": "belongs on ClawHub"
  },
  {
    "number": 35262,
    "action": "closed",
    "reason": "already implemented on main"
  },
  {
    "number": 35291,
    "action": "closed",
    "reason": "already implemented on main"
  },
  {
    "number": 35336,
    "action": "closed",
    "reason": "belongs on ClawHub"
  },
  {
    "number": 35377,
    "action": "closed",
    "reason": "already implemented on main"
  },
  {
    "number": 35426,
    "action": "closed",
    "reason": "cannot reproduce on current main"
  },
  {
    "number": 35466,
    "action": "closed",
    "reason": "already implemented on main"
  },
  {
    "number": 35532,
    "action": "closed",
    "reason": "already implemented on main"
  },
  {
    "number": 35653,
    "action": "closed",
    "reason": "already implemented on main"
  },
  {
    "number": 35669,
    "action": "closed",
    "reason": "already implemented on main"
  },
  {
    "number": 35802,
    "action": "closed",
    "reason": "already implemented on main"
  },
  {
    "number": 35804,
    "action": "closed",
    "reason": "already implemented on main"
  },
  {
    "number": 35805,
    "action": "closed",
    "reason": "belongs on ClawHub"
  },
  {
    "number": 35922,
    "action": "closed",
    "reason": "already implemented on main"
  },
  {
    "number": 36012,
    "action": "closed",
    "reason": "not actionable"
  },
  {
    "number": 36025,
    "action": "closed",
    "reason": "belongs on ClawHub"
  },
  {
    "number": 36109,
    "action": "closed",
    "reason": "already implemented on main"
  },
  {
    "number": 36163,
    "action": "closed",
    "reason": "belongs on ClawHub"
  },
  {
    "number": 36323,
    "action": "closed",
    "reason": "already implemented on main"
  },
  {
    "number": 36399,
    "action": "closed",
    "reason": "cannot reproduce on current main"
  },
  {
    "number": 36410,
    "action": "skipped_already_closed",
    "reason": "state is closed"
  },
  {
    "number": 36411,
    "action": "skipped_already_closed",
    "reason": "state is closed"
  },
  {
    "number": 36440,
    "action": "closed",
    "reason": "already implemented on main"
  },
  {
    "number": 36458,
    "action": "closed",
    "reason": "already implemented on main"
  },
  {
    "number": 36640,
    "action": "closed",
    "reason": "already implemented on main"
  },
  {
    "number": 36881,
    "action": "closed",
    "reason": "already implemented on main"
  },
  {
    "number": 36990,
    "action": "closed",
    "reason": "belongs on ClawHub"
  },
  {
    "number": 37022,
    "action": "closed",
    "reason": "already implemented on main"
  },
  {
    "number": 37083,
    "action": "closed",
    "reason": "already implemented on main"
  },
  {
    "number": 37094,
    "action": "closed",
    "reason": "already implemented on main"
  },
  {
    "number": 37118,
    "action": "closed",
    "reason": "already implemented on main"
  },
  {
    "number": 37136,
    "action": "skipped_already_closed",
    "reason": "state is closed"
  },
  {
    "number": 37142,
    "action": "skipped_already_closed",
    "reason": "state is closed"
  },
  {
    "number": 37150,
    "action": "closed",
    "reason": "already implemented on main"
  },
  {
    "number": 37198,
    "action": "closed",
    "reason": "already implemented on main"
  },
  {
    "number": 37220,
    "action": "closed",
    "reason": "already implemented on main"
  },
  {
    "number": 37225,
    "action": "closed",
    "reason": "belongs on ClawHub"
  },
  {
    "number": 37230,
    "action": "closed",
    "reason": "already implemented on main"
  },
  {
    "number": 37235,
    "action": "closed",
    "reason": "already implemented on main"
  },
  {
    "number": 37250,
    "action": "closed",
    "reason": "already implemented on main"
  },
  {
    "number": 37252,
    "action": "closed",
    "reason": "already implemented on main"
  },
  {
    "number": 37256,
    "action": "closed",
    "reason": "not actionable"
  },
  {
    "number": 37258,
    "action": "closed",
    "reason": "already implemented on main"
  },
  {
    "number": 37303,
    "action": "closed",
    "reason": "already implemented on main"
  },
  {
    "number": 37306,
    "action": "closed",
    "reason": "not actionable"
  },
  {
    "number": 37307,
    "action": "closed",
    "reason": "already implemented on main"
  },
  {
    "number": 37315,
    "action": "closed",
    "reason": "already implemented on main"
  },
  {
    "number": 37322,
    "action": "closed",
    "reason": "already implemented on main"
  },
  {
    "number": 37323,
    "action": "closed",
    "reason": "already implemented on main"
  },
  {
    "number": 37344,
    "action": "closed",
    "reason": "already implemented on main"
  },
  {
    "number": 37374,
    "action": "closed",
    "reason": "already implemented on main"
  },
  {
    "number": 37431,
    "action": "closed",
    "reason": "already implemented on main"
  },
  {
    "number": 37432,
    "action": "closed",
    "reason": "already implemented on main"
  },
  {
    "number": 37457,
    "action": "closed",
    "reason": "cannot reproduce on current main"
  },
  {
    "number": 37463,
    "action": "closed",
    "reason": "already implemented on main"
  },
  {
    "number": 37465,
    "action": "closed",
    "reason": "cannot reproduce on current main"
  },
  {
    "number": 37476,
    "action": "closed",
    "reason": "already implemented on main"
  },
  {
    "number": 37497,
    "action": "closed",
    "reason": "already implemented on main"
  },
  {
    "number": 37499,
    "action": "closed",
    "reason": "already implemented on main"
  },
  {
    "number": 37507,
    "action": "skipped_already_closed",
    "reason": "state is closed"
  },
  {
    "number": 37544,
    "action": "closed",
    "reason": "already implemented on main"
  },
  {
    "number": 37548,
    "action": "closed",
    "reason": "already implemented on main"
  },
  {
    "number": 37553,
    "action": "closed",
    "reason": "already implemented on main"
  },
  {
    "number": 37561,
    "action": "skipped_already_closed",
    "reason": "state is closed"
  },
  {
    "number": 37564,
    "action": "closed",
    "reason": "already implemented on main"
  },
  {
    "number": 37565,
    "action": "closed",
    "reason": "already implemented on main"
  },
  {
    "number": 37566,
    "action": "skipped_changed_since_review",
    "reason": "snapshot changed"
  },
  {
    "number": 37571,
    "action": "skipped_changed_since_review",
    "reason": "snapshot changed"
  },
  {
    "number": 37579,
    "action": "closed",
    "reason": "already implemented on main"
  },
  {
    "number": 37593,
    "action": "skipped_already_closed",
    "reason": "state is closed"
  },
  {
    "number": 37595,
    "action": "closed",
    "reason": "already implemented on main"
  },
  {
    "number": 37605,
    "action": "skipped_changed_since_review",
    "reason": "snapshot changed"
  },
  {
    "number": 37623,
    "action": "skipped_changed_since_review",
    "reason": "snapshot changed"
  },
  {
    "number": 37633,
    "action": "skipped_changed_since_review",
    "reason": "updated_at changed"
  },
  {
    "number": 37635,
    "action": "closed",
    "reason": "already implemented on main"
  },
  {
    "number": 37636,
    "action": "skipped_already_closed",
    "reason": "state is closed"
  },
  {
    "number": 37645,
    "action": "skipped_changed_since_review",
    "reason": "snapshot changed"
  },
  {
    "number": 37655,
    "action": "closed",
    "reason": "already implemented on main"
  },
  {
    "number": 37657,
    "action": "closed",
    "reason": "cannot reproduce on current main"
  },
  {
    "number": 37667,
    "action": "closed",
    "reason": "already implemented on main"
  },
  {
    "number": 37672,
    "action": "closed",
    "reason": "already implemented on main"
  },
  {
    "number": 37675,
    "action": "closed",
    "reason": "already implemented on main"
  },
  {
    "number": 37677,
    "action": "closed",
    "reason": "cannot reproduce on current main"
  },
  {
    "number": 37700,
    "action": "skipped_already_closed",
    "reason": "state is closed"
  },
  {
    "number": 37701,
    "action": "closed",
    "reason": "already implemented on main"
  },
  {
    "number": 37702,
    "action": "closed",
    "reason": "already implemented on main"
  },
  {
    "number": 37709,
    "action": "skipped_already_closed",
    "reason": "state is closed"
  },
  {
    "number": 37716,
    "action": "closed",
    "reason": "already implemented on main"
  },
  {
    "number": 37734,
    "action": "skipped_already_closed",
    "reason": "state is closed"
  },
  {
    "number": 37743,
    "action": "closed",
    "reason": "already implemented on main"
  },
  {
    "number": 37749,
    "action": "closed",
    "reason": "already implemented on main"
  },
  {
    "number": 37752,
    "action": "closed",
    "reason": "already implemented on main"
  },
  {
    "number": 37757,
    "action": "closed",
    "reason": "cannot reproduce on current main"
  },
  {
    "number": 37758,
    "action": "closed",
    "reason": "already implemented on main"
  },
  {
    "number": 37765,
    "action": "closed",
    "reason": "already implemented on main"
  },
  {
    "number": 37832,
    "action": "closed",
    "reason": "already implemented on main"
  },
  {
    "number": 37844,
    "action": "closed",
    "reason": "already implemented on main"
  },
  {
    "number": 37846,
    "action": "closed",
    "reason": "already implemented on main"
  },
  {
    "number": 37852,
    "action": "closed",
    "reason": "already implemented on main"
  },
  {
    "number": 37854,
    "action": "skipped_already_closed",
    "reason": "state is closed"
  },
  {
    "number": 37857,
    "action": "closed",
    "reason": "already implemented on main"
  },
  {
    "number": 37863,
    "action": "skipped_already_closed",
    "reason": "state is closed"
  },
  {
    "number": 37865,
    "action": "closed",
    "reason": "already implemented on main"
  },
  {
    "number": 37869,
    "action": "closed",
    "reason": "already implemented on main"
  },
  {
    "number": 37874,
    "action": "closed",
    "reason": "already implemented on main"
  },
  {
    "number": 37904,
    "action": "skipped_already_closed",
    "reason": "state is closed"
  },
  {
    "number": 37907,
    "action": "closed",
    "reason": "already implemented on main"
  },
  {
    "number": 37913,
    "action": "skipped_changed_since_review",
    "reason": "snapshot changed"
  },
  {
    "number": 37939,
    "action": "closed",
    "reason": "already implemented on main"
  },
  {
    "number": 37953,
    "action": "skipped_already_closed",
    "reason": "state is closed"
  },
  {
    "number": 37968,
    "action": "skipped_already_closed",
    "reason": "state is closed"
  },
  {
    "number": 37970,
    "action": "skipped_already_closed",
    "reason": "state is closed"
  },
  {
    "number": 37983,
    "action": "skipped_changed_since_review",
    "reason": "snapshot changed"
  },
  {
    "number": 38032,
    "action": "skipped_already_closed",
    "reason": "state is closed"
  },
  {
    "number": 38041,
    "action": "skipped_already_closed",
    "reason": "state is closed"
  },
  {
    "number": 38050,
    "action": "skipped_already_closed",
    "reason": "state is closed"
  },
  {
    "number": 38055,
    "action": "closed",
    "reason": "already implemented on main"
  },
  {
    "number": 38058,
    "action": "closed",
    "reason": "already implemented on main"
  },
  {
    "number": 38059,
    "action": "closed",
    "reason": "already implemented on main"
  },
  {
    "number": 38061,
    "action": "closed",
    "reason": "already implemented on main"
  },
  {
    "number": 38067,
    "action": "closed",
    "reason": "already implemented on main"
  },
  {
    "number": 38077,
    "action": "closed",
    "reason": "belongs on ClawHub"
  },
  {
    "number": 38078,
    "action": "closed",
    "reason": "already implemented on main"
  },
  {
    "number": 38080,
    "action": "closed",
    "reason": "cannot reproduce on current main"
  },
  {
    "number": 38083,
    "action": "closed",
    "reason": "already implemented on main"
  },
  {
    "number": 38120,
    "action": "skipped_already_closed",
    "reason": "state is closed"
  },
  {
    "number": 38124,
    "action": "closed",
    "reason": "already implemented on main"
  },
  {
    "number": 38125,
    "action": "closed",
    "reason": "already implemented on main"
  },
  {
    "number": 38131,
    "action": "closed",
    "reason": "cannot reproduce on current main"
  },
  {
    "number": 38141,
    "action": "skipped_changed_since_review",
    "reason": "snapshot changed"
  },
  {
    "number": 38145,
    "action": "closed",
    "reason": "already implemented on main"
  },
  {
    "number": 38155,
    "action": "closed",
    "reason": "already implemented on main"
  },
  {
    "number": 38166,
    "action": "closed",
    "reason": "already implemented on main"
  },
  {
    "number": 38169,
    "action": "closed",
    "reason": "cannot reproduce on current main"
  },
  {
    "number": 38215,
    "action": "skipped_changed_since_review",
    "reason": "snapshot changed"
  },
  {
    "number": 38216,
    "action": "skipped_changed_since_review",
    "reason": "snapshot changed"
  },
  {
    "number": 38217,
    "action": "closed",
    "reason": "already implemented on main"
  },
  {
    "number": 38223,
    "action": "closed",
    "reason": "already implemented on main"
  },
  {
    "number": 38244,
    "action": "closed",
    "reason": "already implemented on main"
  },
  {
    "number": 38256,
    "action": "closed",
    "reason": "already implemented on main"
  },
  {
    "number": 38262,
    "action": "closed",
    "reason": "already implemented on main"
  },
  {
    "number": 38268,
    "action": "closed",
    "reason": "already implemented on main"
  },
  {
    "number": 38270,
    "action": "closed",
    "reason": "already implemented on main"
  },
  {
    "number": 38272,
    "action": "closed",
    "reason": "already implemented on main"
  },
  {
    "number": 38273,
    "action": "closed",
    "reason": "already implemented on main"
  },
  {
    "number": 38274,
    "action": "closed",
    "reason": "already implemented on main"
  },
  {
    "number": 38275,
    "action": "closed",
    "reason": "already implemented on main"
  },
  {
    "number": 38279,
    "action": "closed",
    "reason": "already implemented on main"
  },
  {
    "number": 38280,
    "action": "closed",
    "reason": "already implemented on main"
  },
  {
    "number": 38298,
    "action": "closed",
    "reason": "cannot reproduce on current main"
  },
  {
    "number": 38300,
    "action": "closed",
    "reason": "already implemented on main"
  },
  {
    "number": 38307,
    "action": "closed",
    "reason": "already implemented on main"
  },
  {
    "number": 38312,
    "action": "closed",
    "reason": "already implemented on main"
  },
  {
    "number": 38313,
    "action": "closed",
    "reason": "already implemented on main"
  },
  {
    "number": 38321,
    "action": "closed",
    "reason": "already implemented on main"
  },
  {
    "number": 38328,
    "action": "closed",
    "reason": "cannot reproduce on current main"
  },
  {
    "number": 38335,
    "action": "closed",
    "reason": "already implemented on main"
  },
  {
    "number": 38336,
    "action": "closed",
    "reason": "cannot reproduce on current main"
  },
  {
    "number": 38339,
    "action": "closed",
    "reason": "belongs on ClawHub"
  },
  {
    "number": 38342,
    "action": "closed",
    "reason": "belongs on ClawHub"
  },
  {
    "number": 38345,
    "action": "closed",
    "reason": "already implemented on main"
  },
  {
    "number": 38370,
    "action": "closed",
    "reason": "already implemented on main"
  },
  {
    "number": 38372,
    "action": "closed",
    "reason": "already implemented on main"
  },
  {
    "number": 38376,
    "action": "closed",
    "reason": "already implemented on main"
  },
  {
    "number": 38384,
    "action": "closed",
    "reason": "already implemented on main"
  },
  {
    "number": 38390,
    "action": "closed",
    "reason": "already implemented on main"
  },
  {
    "number": 38394,
    "action": "closed",
    "reason": "already implemented on main"
  },
  {
    "number": 38401,
    "action": "closed",
    "reason": "already implemented on main"
  },
  {
    "number": 38403,
    "action": "closed",
    "reason": "already implemented on main"
  },
  {
    "number": 38404,
    "action": "closed",
    "reason": "belongs on ClawHub"
  },
  {
    "number": 38409,
    "action": "closed",
    "reason": "already implemented on main"
  },
  {
    "number": 38411,
    "action": "closed",
    "reason": "already implemented on main"
  },
  {
    "number": 38412,
    "action": "closed",
    "reason": "already implemented on main"
  },
  {
    "number": 38416,
    "action": "closed",
    "reason": "already implemented on main"
  },
  {
    "number": 38417,
    "action": "closed",
    "reason": "belongs on ClawHub"
  },
  {
    "number": 38432,
    "action": "closed",
    "reason": "already implemented on main"
  },
  {
    "number": 38435,
    "action": "closed",
    "reason": "already implemented on main"
  },
  {
    "number": 38446,
    "action": "closed",
    "reason": "already implemented on main"
  },
  {
    "number": 38447,
    "action": "closed",
    "reason": "already implemented on main"
  },
  {
    "number": 38451,
    "action": "closed",
    "reason": "already implemented on main"
  },
  {
    "number": 38455,
    "action": "closed",
    "reason": "already implemented on main"
  },
  {
    "number": 38457,
    "action": "closed",
    "reason": "already implemented on main"
  },
  {
    "number": 38459,
    "action": "closed",
    "reason": "already implemented on main"
  },
  {
    "number": 38468,
    "action": "closed",
    "reason": "already implemented on main"
  },
  {
    "number": 38469,
    "action": "closed",
    "reason": "already implemented on main"
  },
  {
    "number": 38471,
    "action": "closed",
    "reason": "already implemented on main"
  },
  {
    "number": 38473,
    "action": "closed",
    "reason": "already implemented on main"
  },
  {
    "number": 38486,
    "action": "closed",
    "reason": "already implemented on main"
  },
  {
    "number": 38487,
    "action": "closed",
    "reason": "already implemented on main"
  },
  {
    "number": 38489,
    "action": "closed",
    "reason": "already implemented on main"
  },
  {
    "number": 38500,
    "action": "closed",
    "reason": "already implemented on main"
  },
  {
    "number": 38504,
    "action": "closed",
    "reason": "already implemented on main"
  },
  {
    "number": 38507,
    "action": "closed",
    "reason": "already implemented on main"
  },
  {
    "number": 38517,
    "action": "closed",
    "reason": "already implemented on main"
  },
  {
    "number": 38526,
    "action": "closed",
    "reason": "cannot reproduce on current main"
  },
  {
    "number": 38532,
    "action": "closed",
    "reason": "already implemented on main"
  },
  {
    "number": 38534,
    "action": "closed",
    "reason": "already implemented on main"
  },
  {
    "number": 38536,
    "action": "closed",
    "reason": "already implemented on main"
  },
  {
    "number": 38549,
    "action": "closed",
    "reason": "belongs on ClawHub"
  },
  {
    "number": 38554,
    "action": "closed",
    "reason": "already implemented on main"
  },
  {
    "number": 38555,
    "action": "closed",
    "reason": "already implemented on main"
  },
  {
    "number": 38563,
    "action": "closed",
    "reason": "cannot reproduce on current main"
  },
  {
    "number": 38567,
    "action": "closed",
    "reason": "already implemented on main"
  },
  {
    "number": 38569,
    "action": "closed",
    "reason": "already implemented on main"
  },
  {
    "number": 38571,
    "action": "closed",
    "reason": "belongs on ClawHub"
  },
  {
    "number": 38577,
    "action": "closed",
    "reason": "already implemented on main"
  },
  {
    "number": 38581,
    "action": "closed",
    "reason": "already implemented on main"
  },
  {
    "number": 38584,
    "action": "closed",
    "reason": "cannot reproduce on current main"
  },
  {
    "number": 38587,
    "action": "closed",
    "reason": "already implemented on main"
  },
  {
    "number": 38599,
    "action": "closed",
    "reason": "already implemented on main"
  },
  {
    "number": 38612,
    "action": "closed",
    "reason": "already implemented on main"
  },
  {
    "number": 38627,
    "action": "closed",
    "reason": "belongs on ClawHub"
  },
  {
    "number": 38632,
    "action": "closed",
    "reason": "already implemented on main"
  },
  {
    "number": 38641,
    "action": "closed",
    "reason": "already implemented on main"
  },
  {
    "number": 38649,
    "action": "closed",
    "reason": "cannot reproduce on current main"
  },
  {
    "number": 38651,
    "action": "closed",
    "reason": "already implemented on main"
  },
  {
    "number": 38663,
    "action": "closed",
    "reason": "already implemented on main"
  },
  {
    "number": 38665,
    "action": "closed",
    "reason": "already implemented on main"
  },
  {
    "number": 38672,
    "action": "closed",
    "reason": "already implemented on main"
  },
  {
    "number": 38674,
    "action": "closed",
    "reason": "cannot reproduce on current main"
  },
  {
    "number": 38679,
    "action": "closed",
    "reason": "already implemented on main"
  },
  {
    "number": 38682,
    "action": "closed",
    "reason": "already implemented on main"
  },
  {
    "number": 38686,
    "action": "closed",
    "reason": "already implemented on main"
  },
  {
    "number": 38693,
    "action": "closed",
    "reason": "already implemented on main"
  },
  {
    "number": 38694,
    "action": "closed",
    "reason": "already implemented on main"
  },
  {
    "number": 38697,
    "action": "closed",
    "reason": "cannot reproduce on current main"
  },
  {
    "number": 38704,
    "action": "closed",
    "reason": "already implemented on main"
  },
  {
    "number": 38707,
    "action": "closed",
    "reason": "cannot reproduce on current main"
  },
  {
    "number": 38719,
    "action": "closed",
    "reason": "already implemented on main"
  },
  {
    "number": 38724,
    "action": "closed",
    "reason": "already implemented on main"
  },
  {
    "number": 38726,
    "action": "closed",
    "reason": "already implemented on main"
  },
  {
    "number": 38755,
    "action": "closed",
    "reason": "already implemented on main"
  },
  {
    "number": 38764,
    "action": "closed",
    "reason": "belongs on ClawHub"
  },
  {
    "number": 38771,
    "action": "closed",
    "reason": "already implemented on main"
  },
  {
    "number": 38777,
    "action": "closed",
    "reason": "already implemented on main"
  },
  {
    "number": 38778,
    "action": "closed",
    "reason": "not actionable"
  },
  {
    "number": 38782,
    "action": "closed",
    "reason": "already implemented on main"
  },
  {
    "number": 38791,
    "action": "closed",
    "reason": "already implemented on main"
  },
  {
    "number": 38795,
    "action": "closed",
    "reason": "already implemented on main"
  },
  {
    "number": 38799,
    "action": "closed",
    "reason": "belongs on ClawHub"
  },
  {
    "number": 38800,
    "action": "closed",
    "reason": "already implemented on main"
  },
  {
    "number": 38801,
    "action": "closed",
    "reason": "already implemented on main"
  },
  {
    "number": 38807,
    "action": "closed",
    "reason": "cannot reproduce on current main"
  },
  {
    "number": 38809,
    "action": "closed",
    "reason": "already implemented on main"
  },
  {
    "number": 38810,
    "action": "skipped_changed_since_review",
    "reason": "updated_at changed"
  },
  {
    "number": 38820,
    "action": "closed",
    "reason": "already implemented on main"
  },
  {
    "number": 38823,
    "action": "closed",
    "reason": "already implemented on main"
  },
  {
    "number": 38824,
    "action": "closed",
    "reason": "already implemented on main"
  },
  {
    "number": 38828,
    "action": "closed",
    "reason": "already implemented on main"
  },
  {
    "number": 38837,
    "action": "closed",
    "reason": "already implemented on main"
  },
  {
    "number": 38838,
    "action": "closed",
    "reason": "already implemented on main"
  },
  {
    "number": 38839,
    "action": "closed",
    "reason": "already implemented on main"
  },
  {
    "number": 38842,
    "action": "closed",
    "reason": "belongs on ClawHub"
  },
  {
    "number": 38847,
    "action": "closed",
    "reason": "already implemented on main"
  },
  {
    "number": 38849,
    "action": "closed",
    "reason": "already implemented on main"
  },
  {
    "number": 38851,
    "action": "closed",
    "reason": "not actionable"
  },
  {
    "number": 38858,
    "action": "closed",
    "reason": "already implemented on main"
  },
  {
    "number": 38867,
    "action": "closed",
    "reason": "cannot reproduce on current main"
  },
  {
    "number": 38872,
    "action": "closed",
    "reason": "already implemented on main"
  },
  {
    "number": 38874,
    "action": "closed",
    "reason": "already implemented on main"
  },
  {
    "number": 38878,
    "action": "closed",
    "reason": "already implemented on main"
  },
  {
    "number": 38887,
    "action": "closed",
    "reason": "already implemented on main"
  },
  {
    "number": 38890,
    "action": "closed",
    "reason": "already implemented on main"
  },
  {
    "number": 38902,
    "action": "closed",
    "reason": "already implemented on main"
  },
  {
    "number": 38903,
    "action": "closed",
    "reason": "cannot reproduce on current main"
  },
  {
    "number": 38908,
    "action": "closed",
    "reason": "already implemented on main"
  },
  {
    "number": 38910,
    "action": "closed",
    "reason": "already implemented on main"
  },
  {
    "number": 38917,
    "action": "closed",
    "reason": "already implemented on main"
  },
  {
    "number": 38925,
    "action": "closed",
    "reason": "already implemented on main"
  },
  {
    "number": 38926,
    "action": "closed",
    "reason": "already implemented on main"
  },
  {
    "number": 38930,
    "action": "closed",
    "reason": "already implemented on main"
  },
  {
    "number": 38933,
    "action": "closed",
    "reason": "already implemented on main"
  },
  {
    "number": 38938,
    "action": "closed",
    "reason": "already implemented on main"
  }
]