[
  {
    "number": 604,
    "action": "review_comment_synced",
    "reason": "updated durable Codex review comment"
  },
  {
    "number": 679,
    "action": "review_comment_synced",
    "reason": "updated durable Codex review comment"
  },
  {
    "number": 692,
    "action": "review_comment_synced",
    "reason": "updated durable Codex review comment"
  },
  {
    "number": 733,
    "action": "review_comment_synced",
    "reason": "updated durable Codex review comment"
  },
  {
    "number": 745,
    "action": "review_comment_synced",
    "reason": "updated durable Codex review comment"
  },
  {
    "number": 752,
    "action": "review_comment_synced",
    "reason": "updated durable Codex review comment"
  },
  {
    "number": 767,
    "action": "review_comment_synced",
    "reason": "updated durable Codex review comment"
  },
  {
    "number": 768,
    "action": "review_comment_synced",
    "reason": "updated durable Codex review comment"
  },
  {
    "number": 779,
    "action": "review_comment_synced",
    "reason": "updated durable Codex review comment"
  },
  {
    "number": 786,
    "action": "review_comment_synced",
    "reason": "updated durable Codex review comment"
  },
  {
    "number": 791,
    "action": "review_comment_synced",
    "reason": "updated durable Codex review comment"
  },
  {
    "number": 804,
    "action": "review_comment_synced",
    "reason": "updated durable Codex review comment"
  },
  {
    "number": 808,
    "action": "review_comment_synced",
    "reason": "updated durable Codex review comment"
  },
  {
    "number": 809,
    "action": "review_comment_synced",
    "reason": "updated durable Codex review comment"
  },
  {
    "number": 817,
    "action": "review_comment_synced",
    "reason": "updated durable Codex review comment"
  },
  {
    "number": 823,
    "action": "review_comment_synced",
    "reason": "updated durable Codex review comment"
  },
  {
    "number": 834,
    "action": "review_comment_synced",
    "reason": "updated durable Codex review comment"
  },
  {
    "number": 850,
    "action": "review_comment_synced",
    "reason": "updated durable Codex review comment"
  },
  {
    "number": 853,
    "action": "review_comment_synced",
    "reason": "updated durable Codex review comment"
  },
  {
    "number": 858,
    "action": "review_comment_synced",
    "reason": "updated durable Codex review comment"
  },
  {
    "number": 868,
    "action": "review_comment_synced",
    "reason": "updated durable Codex review comment"
  },
  {
    "number": 880,
    "action": "review_comment_synced",
    "reason": "updated durable Codex review comment"
  },
  {
    "number": 883,
    "action": "review_comment_synced",
    "reason": "updated durable Codex review comment"
  },
  {
    "number": 887,
    "action": "review_comment_synced",
    "reason": "updated durable Codex review comment"
  },
  {
    "number": 889,
    "action": "review_comment_synced",
    "reason": "updated durable Codex review comment"
  },
  {
    "number": 901,
    "action": "review_comment_synced",
    "reason": "updated durable Codex review comment"
  },
  {
    "number": 903,
    "action": "review_comment_synced",
    "reason": "updated durable Codex review comment"
  },
  {
    "number": 904,
    "action": "review_comment_synced",
    "reason": "updated durable Codex review comment"
  },
  {
    "number": 928,
    "action": "review_comment_synced",
    "reason": "updated durable Codex review comment"
  },
  {
    "number": 933,
    "action": "review_comment_synced",
    "reason": "updated durable Codex review comment"
  },
  {
    "number": 941,
    "action": "review_comment_synced",
    "reason": "updated durable Codex review comment"
  },
  {
    "number": 951,
    "action": "review_comment_synced",
    "reason": "updated durable Codex review comment"
  },
  {
    "number": 954,
    "action": "review_comment_synced",
    "reason": "updated durable Codex review comment"
  },
  {
    "number": 960,
    "action": "review_comment_synced",
    "reason": "updated durable Codex review comment"
  },
  {
    "number": 967,
    "action": "review_comment_synced",
    "reason": "updated durable Codex review comment"
  },
  {
    "number": 971,
    "action": "review_comment_synced",
    "reason": "updated durable Codex review comment"
  },
  {
    "number": 972,
    "action": "review_comment_synced",
    "reason": "updated durable Codex review comment"
  },
  {
    "number": 974,
    "action": "review_comment_synced",
    "reason": "updated durable Codex review comment"
  },
  {
    "number": 975,
    "action": "review_comment_synced",
    "reason": "updated durable Codex review comment"
  },
  {
    "number": 992,
    "action": "review_comment_synced",
    "reason": "updated durable Codex review comment"
  },
  {
    "number": 995,
    "action": "review_comment_synced",
    "reason": "updated durable Codex review comment"
  },
  {
    "number": 997,
    "action": "review_comment_synced",
    "reason": "updated durable Codex review comment"
  },
  {
    "number": 998,
    "action": "review_comment_synced",
    "reason": "updated durable Codex review comment"
  },
  {
    "number": 1010,
    "action": "review_comment_synced",
    "reason": "updated durable Codex review comment"
  },
  {
    "number": 1015,
    "action": "review_comment_synced",
    "reason": "updated durable Codex review comment"
  },
  {
    "number": 1017,
    "action": "review_comment_synced",
    "reason": "updated durable Codex review comment"
  },
  {
    "number": 1018,
    "action": "review_comment_synced",
    "reason": "updated durable Codex review comment"
  },
  {
    "number": 1020,
    "action": "review_comment_synced",
    "reason": "updated durable Codex review comment"
  },
  {
    "number": 1028,
    "action": "review_comment_synced",
    "reason": "updated durable Codex review comment"
  },
  {
    "number": 1032,
    "action": "review_comment_synced",
    "reason": "updated durable Codex review comment"
  },
  {
    "number": 1035,
    "action": "review_comment_synced",
    "reason": "updated durable Codex review comment"
  },
  {
    "number": 1039,
    "action": "review_comment_synced",
    "reason": "updated durable Codex review comment"
  },
  {
    "number": 1040,
    "action": "review_comment_synced",
    "reason": "updated durable Codex review comment"
  },
  {
    "number": 1041,
    "action": "review_comment_synced",
    "reason": "updated durable Codex review comment"
  },
  {
    "number": 1043,
    "action": "review_comment_synced",
    "reason": "updated durable Codex review comment"
  },
  {
    "number": 1044,
    "action": "review_comment_synced",
    "reason": "updated durable Codex review comment"
  },
  {
    "number": 1048,
    "action": "review_comment_synced",
    "reason": "updated durable Codex review comment"
  },
  {
    "number": 1049,
    "action": "review_comment_synced",
    "reason": "updated durable Codex review comment"
  },
  {
    "number": 1052,
    "action": "review_comment_synced",
    "reason": "updated durable Codex review comment"
  },
  {
    "number": 1053,
    "action": "review_comment_synced",
    "reason": "updated durable Codex review comment"
  },
  {
    "number": 1054,
    "action": "review_comment_synced",
    "reason": "updated durable Codex review comment"
  },
  {
    "number": 1063,
    "action": "review_comment_synced",
    "reason": "updated durable Codex review comment"
  },
  {
    "number": 1068,
    "action": "review_comment_synced",
    "reason": "updated durable Codex review comment"
  },
  {
    "number": 1080,
    "action": "review_comment_synced",
    "reason": "updated durable Codex review comment"
  },
  {
    "number": 1085,
    "action": "review_comment_synced",
    "reason": "updated durable Codex review comment"
  },
  {
    "number": 1088,
    "action": "review_comment_synced",
    "reason": "updated durable Codex review comment"
  },
  {
    "number": 1089,
    "action": "review_comment_synced",
    "reason": "updated durable Codex review comment"
  },
  {
    "number": 1092,
    "action": "review_comment_synced",
    "reason": "updated durable Codex review comment"
  },
  {
    "number": 1094,
    "action": "review_comment_synced",
    "reason": "updated durable Codex review comment"
  },
  {
    "number": 1100,
    "action": "review_comment_synced",
    "reason": "updated durable Codex review comment"
  },
  {
    "number": 1103,
    "action": "review_comment_synced",
    "reason": "updated durable Codex review comment"
  },
  {
    "number": 1110,
    "action": "review_comment_synced",
    "reason": "updated durable Codex review comment"
  },
  {
    "number": 1114,
    "action": "review_comment_synced",
    "reason": "updated durable Codex review comment"
  },
  {
    "number": 1116,
    "action": "review_comment_synced",
    "reason": "updated durable Codex review comment"
  },
  {
    "number": 1119,
    "action": "review_comment_synced",
    "reason": "updated durable Codex review comment"
  },
  {
    "number": 1121,
    "action": "review_comment_synced",
    "reason": "updated durable Codex review comment"
  },
  {
    "number": 1122,
    "action": "review_comment_synced",
    "reason": "updated durable Codex review comment"
  },
  {
    "number": 1125,
    "action": "review_comment_synced",
    "reason": "updated durable Codex review comment"
  },
  {
    "number": 1129,
    "action": "review_comment_synced",
    "reason": "updated durable Codex review comment"
  },
  {
    "number": 1133,
    "action": "review_comment_synced",
    "reason": "updated durable Codex review comment"
  },
  {
    "number": 1147,
    "action": "review_comment_synced",
    "reason": "updated durable Codex review comment"
  },
  {
    "number": 1148,
    "action": "review_comment_synced",
    "reason": "updated durable Codex review comment"
  },
  {
    "number": 1152,
    "action": "review_comment_synced",
    "reason": "updated durable Codex review comment"
  },
  {
    "number": 1153,
    "action": "review_comment_synced",
    "reason": "updated durable Codex review comment"
  },
  {
    "number": 1155,
    "action": "review_comment_synced",
    "reason": "updated durable Codex review comment"
  },
  {
    "number": 1156,
    "action": "review_comment_synced",
    "reason": "updated durable Codex review comment"
  },
  {
    "number": 1164,
    "action": "review_comment_synced",
    "reason": "updated durable Codex review comment"
  },
  {
    "number": 1168,
    "action": "review_comment_synced",
    "reason": "updated durable Codex review comment"
  },
  {
    "number": 1179,
    "action": "review_comment_synced",
    "reason": "updated durable Codex review comment"
  },
  {
    "number": 1180,
    "action": "review_comment_synced",
    "reason": "updated durable Codex review comment"
  },
  {
    "number": 1181,
    "action": "review_comment_synced",
    "reason": "updated durable Codex review comment"
  },
  {
    "number": 1186,
    "action": "review_comment_synced",
    "reason": "updated durable Codex review comment"
  },
  {
    "number": 1199,
    "action": "review_comment_synced",
    "reason": "updated durable Codex review comment"
  },
  {
    "number": 1201,
    "action": "review_comment_synced",
    "reason": "updated durable Codex review comment"
  },
  {
    "number": 1207,
    "action": "review_comment_synced",
    "reason": "updated durable Codex review comment"
  },
  {
    "number": 1212,
    "action": "review_comment_synced",
    "reason": "updated durable Codex review comment"
  },
  {
    "number": 1217,
    "action": "review_comment_synced",
    "reason": "updated durable Codex review comment"
  },
  {
    "number": 1230,
    "action": "review_comment_synced",
    "reason": "updated durable Codex review comment"
  },
  {
    "number": 1233,
    "action": "review_comment_synced",
    "reason": "updated durable Codex review comment"
  },
  {
    "number": 1256,
    "action": "review_comment_synced",
    "reason": "updated durable Codex review comment"
  },
  {
    "number": 1275,
    "action": "review_comment_synced",
    "reason": "updated durable Codex review comment"
  },
  {
    "number": 1287,
    "action": "review_comment_synced",
    "reason": "updated durable Codex review comment"
  },
  {
    "number": 1292,
    "action": "review_comment_synced",
    "reason": "updated durable Codex review comment"
  },
  {
    "number": 1368,
    "action": "review_comment_synced",
    "reason": "updated durable Codex review comment"
  },
  {
    "number": 1370,
    "action": "review_comment_synced",
    "reason": "updated durable Codex review comment"
  },
  {
    "number": 1371,
    "action": "review_comment_synced",
    "reason": "updated durable Codex review comment"
  },
  {
    "number": 1374,
    "action": "review_comment_synced",
    "reason": "updated durable Codex review comment"
  },
  {
    "number": 1376,
    "action": "review_comment_synced",
    "reason": "updated durable Codex review comment"
  },
  {
    "number": 1377,
    "action": "review_comment_synced",
    "reason": "updated durable Codex review comment"
  },
  {
    "number": 1379,
    "action": "review_comment_synced",
    "reason": "updated durable Codex review comment"
  },
  {
    "number": 1387,
    "action": "review_comment_synced",
    "reason": "updated durable Codex review comment"
  },
  {
    "number": 1389,
    "action": "review_comment_synced",
    "reason": "updated durable Codex review comment"
  },
  {
    "number": 1391,
    "action": "review_comment_synced",
    "reason": "updated durable Codex review comment"
  },
  {
    "number": 1393,
    "action": "review_comment_synced",
    "reason": "updated durable Codex review comment"
  },
  {
    "number": 7057,
    "action": "review_comment_synced",
    "reason": "updated durable Codex review comment"
  },
  {
    "number": 1396,
    "action": "review_comment_synced",
    "reason": "updated durable Codex review comment"
  },
  {
    "number": 1398,
    "action": "review_comment_synced",
    "reason": "updated durable Codex review comment"
  },
  {
    "number": 1400,
    "action": "review_comment_synced",
    "reason": "updated durable Codex review comment"
  },
  {
    "number": 1402,
    "action": "review_comment_synced",
    "reason": "updated durable Codex review comment"
  },
  {
    "number": 1403,
    "action": "review_comment_synced",
    "reason": "updated durable Codex review comment"
  },
  {
    "number": 14593,
    "action": "review_comment_synced",
    "reason": "updated durable Codex review comment"
  },
  {
    "number": 1406,
    "action": "review_comment_synced",
    "reason": "updated durable Codex review comment"
  },
  {
    "number": 1409,
    "action": "review_comment_synced",
    "reason": "updated durable Codex review comment"
  },
  {
    "number": 1411,
    "action": "review_comment_synced",
    "reason": "updated durable Codex review comment"
  },
  {
    "number": 1415,
    "action": "review_comment_synced",
    "reason": "updated durable Codex review comment"
  },
  {
    "number": 1416,
    "action": "review_comment_synced",
    "reason": "updated durable Codex review comment"
  },
  {
    "number": 1417,
    "action": "review_comment_synced",
    "reason": "updated durable Codex review comment"
  },
  {
    "number": 1418,
    "action": "review_comment_synced",
    "reason": "updated durable Codex review comment"
  },
  {
    "number": 1421,
    "action": "review_comment_synced",
    "reason": "updated durable Codex review comment"
  },
  {
    "number": 1423,
    "action": "review_comment_synced",
    "reason": "updated durable Codex review comment"
  },
  {
    "number": 1425,
    "action": "review_comment_synced",
    "reason": "updated durable Codex review comment"
  },
  {
    "number": 1426,
    "action": "review_comment_synced",
    "reason": "updated durable Codex review comment"
  },
  {
    "number": 1427,
    "action": "review_comment_synced",
    "reason": "updated durable Codex review comment"
  },
  {
    "number": 1431,
    "action": "review_comment_synced",
    "reason": "updated durable Codex review comment"
  },
  {
    "number": 1432,
    "action": "review_comment_synced",
    "reason": "updated durable Codex review comment"
  },
  {
    "number": 1433,
    "action": "review_comment_synced",
    "reason": "updated durable Codex review comment"
  },
  {
    "number": 1434,
    "action": "review_comment_synced",
    "reason": "updated durable Codex review comment"
  },
  {
    "number": 1435,
    "action": "review_comment_synced",
    "reason": "updated durable Codex review comment"
  },
  {
    "number": 1442,
    "action": "review_comment_synced",
    "reason": "updated durable Codex review comment"
  },
  {
    "number": 1443,
    "action": "review_comment_synced",
    "reason": "updated durable Codex review comment"
  },
  {
    "number": 1444,
    "action": "review_comment_synced",
    "reason": "updated durable Codex review comment"
  },
  {
    "number": 1446,
    "action": "review_comment_synced",
    "reason": "updated durable Codex review comment"
  },
  {
    "number": 1447,
    "action": "review_comment_synced",
    "reason": "updated durable Codex review comment"
  },
  {
    "number": 1450,
    "action": "review_comment_synced",
    "reason": "updated durable Codex review comment"
  },
  {
    "number": 1451,
    "action": "review_comment_synced",
    "reason": "updated durable Codex review comment"
  },
  {
    "number": 1457,
    "action": "review_comment_synced",
    "reason": "updated durable Codex review comment"
  },
  {
    "number": 1462,
    "action": "review_comment_synced",
    "reason": "updated durable Codex review comment"
  },
  {
    "number": 1463,
    "action": "review_comment_synced",
    "reason": "updated durable Codex review comment"
  },
  {
    "number": 1465,
    "action": "review_comment_synced",
    "reason": "updated durable Codex review comment"
  },
  {
    "number": 1471,
    "action": "review_comment_synced",
    "reason": "updated durable Codex review comment"
  },
  {
    "number": 1472,
    "action": "review_comment_synced",
    "reason": "updated durable Codex review comment"
  },
  {
    "number": 1473,
    "action": "review_comment_synced",
    "reason": "updated durable Codex review comment"
  },
  {
    "number": 18915,
    "action": "review_comment_synced",
    "reason": "updated durable Codex review comment"
  },
  {
    "number": 1480,
    "action": "review_comment_synced",
    "reason": "updated durable Codex review comment"
  },
  {
    "number": 1483,
    "action": "review_comment_synced",
    "reason": "updated durable Codex review comment"
  },
  {
    "number": 1494,
    "action": "review_comment_synced",
    "reason": "updated durable Codex review comment"
  },
  {
    "number": 1495,
    "action": "review_comment_synced",
    "reason": "updated durable Codex review comment"
  },
  {
    "number": 1500,
    "action": "review_comment_synced",
    "reason": "updated durable Codex review comment"
  },
  {
    "number": 1501,
    "action": "review_comment_synced",
    "reason": "updated durable Codex review comment"
  },
  {
    "number": 1503,
    "action": "review_comment_synced",
    "reason": "updated durable Codex review comment"
  },
  {
    "number": 1509,
    "action": "review_comment_synced",
    "reason": "updated durable Codex review comment"
  },
  {
    "number": 1511,
    "action": "review_comment_synced",
    "reason": "updated durable Codex review comment"
  },
  {
    "number": 1514,
    "action": "review_comment_synced",
    "reason": "updated durable Codex review comment"
  },
  {
    "number": 1516,
    "action": "review_comment_synced",
    "reason": "updated durable Codex review comment"
  },
  {
    "number": 1518,
    "action": "review_comment_synced",
    "reason": "updated durable Codex review comment"
  },
  {
    "number": 1519,
    "action": "review_comment_synced",
    "reason": "updated durable Codex review comment"
  },
  {
    "number": 1521,
    "action": "review_comment_synced",
    "reason": "updated durable Codex review comment"
  },
  {
    "number": 1522,
    "action": "review_comment_synced",
    "reason": "updated durable Codex review comment"
  },
  {
    "number": 1524,
    "action": "review_comment_synced",
    "reason": "updated durable Codex review comment"
  },
  {
    "number": 1525,
    "action": "review_comment_synced",
    "reason": "updated durable Codex review comment"
  },
  {
    "number": 1526,
    "action": "review_comment_synced",
    "reason": "updated durable Codex review comment"
  },
  {
    "number": 1528,
    "action": "review_comment_synced",
    "reason": "updated durable Codex review comment"
  },
  {
    "number": 1533,
    "action": "review_comment_synced",
    "reason": "updated durable Codex review comment"
  },
  {
    "number": 1534,
    "action": "review_comment_synced",
    "reason": "updated durable Codex review comment"
  },
  {
    "number": 1535,
    "action": "review_comment_synced",
    "reason": "updated durable Codex review comment"
  },
  {
    "number": 1538,
    "action": "review_comment_synced",
    "reason": "updated durable Codex review comment"
  },
  {
    "number": 1539,
    "action": "review_comment_synced",
    "reason": "updated durable Codex review comment"
  },
  {
    "number": 1540,
    "action": "review_comment_synced",
    "reason": "updated durable Codex review comment"
  },
  {
    "number": 20802,
    "action": "review_comment_synced",
    "reason": "updated durable Codex review comment"
  },
  {
    "number": 1543,
    "action": "review_comment_synced",
    "reason": "updated durable Codex review comment"
  },
  {
    "number": 1551,
    "action": "review_comment_synced",
    "reason": "updated durable Codex review comment"
  },
  {
    "number": 1552,
    "action": "review_comment_synced",
    "reason": "updated durable Codex review comment"
  },
  {
    "number": 1554,
    "action": "review_comment_synced",
    "reason": "updated durable Codex review comment"
  },
  {
    "number": 1559,
    "action": "review_comment_synced",
    "reason": "updated durable Codex review comment"
  },
  {
    "number": 1563,
    "action": "review_comment_synced",
    "reason": "updated durable Codex review comment"
  },
  {
    "number": 1565,
    "action": "review_comment_synced",
    "reason": "updated durable Codex review comment"
  },
  {
    "number": 1568,
    "action": "review_comment_synced",
    "reason": "updated durable Codex review comment"
  },
  {
    "number": 1569,
    "action": "review_comment_synced",
    "reason": "updated durable Codex review comment"
  },
  {
    "number": 1571,
    "action": "review_comment_synced",
    "reason": "updated durable Codex review comment"
  },
  {
    "number": 1576,
    "action": "review_comment_synced",
    "reason": "updated durable Codex review comment"
  },
  {
    "number": 1577,
    "action": "review_comment_synced",
    "reason": "updated durable Codex review comment"
  },
  {
    "number": 1578,
    "action": "review_comment_synced",
    "reason": "updated durable Codex review comment"
  },
  {
    "number": 1580,
    "action": "review_comment_synced",
    "reason": "updated durable Codex review comment"
  },
  {
    "number": 1582,
    "action": "review_comment_synced",
    "reason": "updated durable Codex review comment"
  },
  {
    "number": 1583,
    "action": "review_comment_synced",
    "reason": "updated durable Codex review comment"
  },
  {
    "number": 1585,
    "action": "review_comment_synced",
    "reason": "updated durable Codex review comment"
  },
  {
    "number": 1586,
    "action": "review_comment_synced",
    "reason": "updated durable Codex review comment"
  },
  {
    "number": 1589,
    "action": "review_comment_synced",
    "reason": "updated durable Codex review comment"
  },
  {
    "number": 1592,
    "action": "review_comment_synced",
    "reason": "updated durable Codex review comment"
  },
  {
    "number": 1595,
    "action": "review_comment_synced",
    "reason": "updated durable Codex review comment"
  },
  {
    "number": 1614,
    "action": "review_comment_synced",
    "reason": "updated durable Codex review comment"
  },
  {
    "number": 1620,
    "action": "review_comment_synced",
    "reason": "updated durable Codex review comment"
  },
  {
    "number": 1621,
    "action": "review_comment_synced",
    "reason": "updated durable Codex review comment"
  },
  {
    "number": 1624,
    "action": "review_comment_synced",
    "reason": "updated durable Codex review comment"
  },
  {
    "number": 1632,
    "action": "review_comment_synced",
    "reason": "updated durable Codex review comment"
  },
  {
    "number": 1639,
    "action": "review_comment_synced",
    "reason": "updated durable Codex review comment"
  },
  {
    "number": 1649,
    "action": "review_comment_synced",
    "reason": "updated durable Codex review comment"
  },
  {
    "number": 1653,
    "action": "review_comment_synced",
    "reason": "updated durable Codex review comment"
  },
  {
    "number": 1657,
    "action": "review_comment_synced",
    "reason": "updated durable Codex review comment"
  },
  {
    "number": 1659,
    "action": "review_comment_synced",
    "reason": "updated durable Codex review comment"
  },
  {
    "number": 1662,
    "action": "review_comment_synced",
    "reason": "updated durable Codex review comment"
  },
  {
    "number": 1668,
    "action": "review_comment_synced",
    "reason": "updated durable Codex review comment"
  },
  {
    "number": 1671,
    "action": "review_comment_synced",
    "reason": "updated durable Codex review comment"
  },
  {
    "number": 1673,
    "action": "review_comment_synced",
    "reason": "updated durable Codex review comment"
  },
  {
    "number": 1675,
    "action": "review_comment_synced",
    "reason": "updated durable Codex review comment"
  },
  {
    "number": 1678,
    "action": "review_comment_synced",
    "reason": "updated durable Codex review comment"
  },
  {
    "number": 1679,
    "action": "review_comment_synced",
    "reason": "updated durable Codex review comment"
  },
  {
    "number": 1680,
    "action": "review_comment_synced",
    "reason": "updated durable Codex review comment"
  },
  {
    "number": 1682,
    "action": "review_comment_synced",
    "reason": "updated durable Codex review comment"
  },
  {
    "number": 1689,
    "action": "review_comment_synced",
    "reason": "updated durable Codex review comment"
  },
  {
    "number": 1690,
    "action": "review_comment_synced",
    "reason": "updated durable Codex review comment"
  },
  {
    "number": 1691,
    "action": "review_comment_synced",
    "reason": "updated durable Codex review comment"
  },
  {
    "number": 1692,
    "action": "review_comment_synced",
    "reason": "updated durable Codex review comment"
  },
  {
    "number": 1703,
    "action": "review_comment_synced",
    "reason": "updated durable Codex review comment"
  },
  {
    "number": 1705,
    "action": "review_comment_synced",
    "reason": "updated durable Codex review comment"
  },
  {
    "number": 1707,
    "action": "review_comment_synced",
    "reason": "updated durable Codex review comment"
  },
  {
    "number": 1717,
    "action": "review_comment_synced",
    "reason": "updated durable Codex review comment"
  },
  {
    "number": 1720,
    "action": "review_comment_synced",
    "reason": "updated durable Codex review comment"
  },
  {
    "number": 1721,
    "action": "review_comment_synced",
    "reason": "updated durable Codex review comment"
  },
  {
    "number": 1733,
    "action": "review_comment_synced",
    "reason": "updated durable Codex review comment"
  },
  {
    "number": 1734,
    "action": "review_comment_synced",
    "reason": "updated durable Codex review comment"
  },
  {
    "number": 1735,
    "action": "review_comment_synced",
    "reason": "updated durable Codex review comment"
  },
  {
    "number": 1738,
    "action": "review_comment_synced",
    "reason": "updated durable Codex review comment"
  },
  {
    "number": 1741,
    "action": "review_comment_synced",
    "reason": "updated durable Codex review comment"
  },
  {
    "number": 1743,
    "action": "review_comment_synced",
    "reason": "updated durable Codex review comment"
  },
  {
    "number": 1744,
    "action": "review_comment_synced",
    "reason": "updated durable Codex review comment"
  },
  {
    "number": 1745,
    "action": "review_comment_synced",
    "reason": "updated durable Codex review comment"
  },
  {
    "number": 1746,
    "action": "review_comment_synced",
    "reason": "updated durable Codex review comment"
  },
  {
    "number": 1748,
    "action": "review_comment_synced",
    "reason": "updated durable Codex review comment"
  },
  {
    "number": 1768,
    "action": "review_comment_synced",
    "reason": "updated durable Codex review comment"
  },
  {
    "number": 1769,
    "action": "review_comment_synced",
    "reason": "updated durable Codex review comment"
  },
  {
    "number": 1770,
    "action": "review_comment_synced",
    "reason": "updated durable Codex review comment"
  },
  {
    "number": 1785,
    "action": "review_comment_synced",
    "reason": "updated durable Codex review comment"
  },
  {
    "number": 1788,
    "action": "review_comment_synced",
    "reason": "updated durable Codex review comment"
  },
  {
    "number": 1798,
    "action": "review_comment_synced",
    "reason": "updated durable Codex review comment"
  },
  {
    "number": 1799,
    "action": "review_comment_synced",
    "reason": "updated durable Codex review comment"
  },
  {
    "number": 1806,
    "action": "review_comment_synced",
    "reason": "updated durable Codex review comment"
  },
  {
    "number": 1808,
    "action": "review_comment_synced",
    "reason": "updated durable Codex review comment"
  },
  {
    "number": 1811,
    "action": "review_comment_synced",
    "reason": "updated durable Codex review comment"
  },
  {
    "number": 1812,
    "action": "review_comment_synced",
    "reason": "updated durable Codex review comment"
  },
  {
    "number": 1813,
    "action": "review_comment_synced",
    "reason": "updated durable Codex review comment"
  },
  {
    "number": 1814,
    "action": "review_comment_synced",
    "reason": "updated durable Codex review comment"
  },
  {
    "number": 1816,
    "action": "review_comment_synced",
    "reason": "updated durable Codex review comment"
  },
  {
    "number": 1817,
    "action": "review_comment_synced",
    "reason": "updated durable Codex review comment"
  },
  {
    "number": 1821,
    "action": "review_comment_synced",
    "reason": "updated durable Codex review comment"
  },
  {
    "number": 1826,
    "action": "review_comment_synced",
    "reason": "updated durable Codex review comment"
  },
  {
    "number": 1829,
    "action": "review_comment_synced",
    "reason": "updated durable Codex review comment"
  },
  {
    "number": 1831,
    "action": "review_comment_synced",
    "reason": "updated durable Codex review comment"
  },
  {
    "number": 1834,
    "action": "review_comment_synced",
    "reason": "updated durable Codex review comment"
  },
  {
    "number": 1838,
    "action": "review_comment_synced",
    "reason": "updated durable Codex review comment"
  },
  {
    "number": 1840,
    "action": "review_comment_synced",
    "reason": "updated durable Codex review comment"
  },
  {
    "number": 1848,
    "action": "review_comment_synced",
    "reason": "updated durable Codex review comment"
  },
  {
    "number": 1852,
    "action": "review_comment_synced",
    "reason": "updated durable Codex review comment"
  },
  {
    "number": 1853,
    "action": "review_comment_synced",
    "reason": "updated durable Codex review comment"
  },
  {
    "number": 1854,
    "action": "review_comment_synced",
    "reason": "updated durable Codex review comment"
  },
  {
    "number": 1855,
    "action": "review_comment_synced",
    "reason": "updated durable Codex review comment"
  },
  {
    "number": 1856,
    "action": "review_comment_synced",
    "reason": "updated durable Codex review comment"
  },
  {
    "number": 1858,
    "action": "review_comment_synced",
    "reason": "updated durable Codex review comment"
  },
  {
    "number": 1859,
    "action": "review_comment_synced",
    "reason": "updated durable Codex review comment"
  },
  {
    "number": 1862,
    "action": "review_comment_synced",
    "reason": "updated durable Codex review comment"
  },
  {
    "number": 1863,
    "action": "review_comment_synced",
    "reason": "updated durable Codex review comment"
  },
  {
    "number": 1864,
    "action": "review_comment_synced",
    "reason": "updated durable Codex review comment"
  },
  {
    "number": 1865,
    "action": "review_comment_synced",
    "reason": "updated durable Codex review comment"
  }
]